mwg_cli/__init__.py
mwg_cli/build.py
mwg_cli/config.py
mwg_cli/exceptions.py
mwg_cli/git.py
mwg_cli/main.py
mwg_cli/plans.py
mwg_cli/terraform.py
mwg_cli/template/cloudbuild.apply.yaml
mwg_cli/template/cloudbuild.yaml
mwg_cli/template/mwg.json
mwg_cli/template/tf/main.tf
mwg_cli/template/tf/variables.tf
mwg_cli-1.1.2.dist-info/METADATA
mwg_cli-1.1.2.dist-info/WHEEL
mwg_cli-1.1.2.dist-info/entry_points.txt
mwg_cli-1.1.2.dist-info/RECORD
