Metadata-Version: 2.1
Name: mwg-cli
Version: 1.1.2
Author-email: chriswacker <christopher.wacker@goaaa.com>
Requires-Python: >=3.7
Requires-Dist: google-cloud-storage
